{
  "project_info": {
    "project_number": "336202647292",
    "project_id": "project-kbm-mobile",
    "storage_bucket": "project-kbm-mobile.appspot.com"
  },
  "client": [
    {
      "client_info": {
        "mobilesdk_app_id": "1:336202647292:android:be0d54411420877cf83979",
        "android_client_info": {
          "package_name": "com.example.project_kbm"
        }
      },
      "oauth_client": [
        {
          "client_id": "336202647292-eqnco7n7dg6rbiu5erd1ee765btniee2.apps.googleusercontent.com",
          "client_type": 1,
          "android_info": {
            "package_name": "com.example.project_kbm",
            "certificate_hash": "575e2871abd0c697b7acfac7c701658a100c016c"
          }
        },
        {
          "client_id": "336202647292-t0ss8aaammn5l4f7v0q8p9m8b20spnau.apps.googleusercontent.com",
          "client_type": 3
        }
      ],
      "api_key": [
        {
          "current_key": "AIzaSyC-lEmSjYiDJurSRRw1YyXjKFpIr-Qk-fU"
        }
      ],
      "services": {
        "appinvite_service": {
          "other_platform_oauth_client": [
            {
              "client_id": "336202647292-7vasftc8dibbeuc5goskcgc5lr4om38p.apps.googleusercontent.com",
              "client_type": 3
            }
          ]
        }
      }
    }
  ],
  "configuration_version": "1"
}